fnvstring/__init__.py
fnvstring/__main__.py
fnvstring/hasher.py
fnvstring-0.9.7.dist-info/LICENSE
fnvstring-0.9.7.dist-info/METADATA
fnvstring-0.9.7.dist-info/WHEEL
fnvstring-0.9.7.dist-info/entry_points.txt
fnvstring-0.9.7.dist-info/top_level.txt
fnvstring-0.9.7.dist-info/RECORD
